check_wheel_contents/__init__.py
check_wheel_contents/__main__.py
check_wheel_contents/checker.py
check_wheel_contents/checks.py
check_wheel_contents/config.py
check_wheel_contents/contents.py
check_wheel_contents/errors.py
check_wheel_contents/filetree.py
check_wheel_contents/util.py
check_wheel_contents-0.6.3.dist-info/METADATA
check_wheel_contents-0.6.3.dist-info/WHEEL
check_wheel_contents-0.6.3.dist-info/entry_points.txt
check_wheel_contents-0.6.3.dist-info/licenses/LICENSE
check_wheel_contents-0.6.3.dist-info/RECORD
